sumsjob/__about__.py
sumsjob/__init__.py
sumsjob/config.py
sumsjob/sacct.py
sumsjob/scancel.py
sumsjob/sinfo.py
sumsjob/srun.py
sumsjob/utils.py
SumsJob-0.7.2.dist-info/LICENSE
SumsJob-0.7.2.dist-info/METADATA
SumsJob-0.7.2.dist-info/WHEEL
SumsJob-0.7.2.dist-info/entry_points.txt
SumsJob-0.7.2.dist-info/top_level.txt
SumsJob-0.7.2.dist-info/RECORD
