Metadata-Version: 2.1
Name: SumsJob
Version: 0.7.2
Summary: A simple Linux command-line utility which submits a job to one of the multiple GPU servers
Home-page: https://github.com/lululxvi/sumsjob
Download-URL: https://github.com/lululxvi/deepxde/tarball/v0.7.2
Author: Lu Lu
Author-email: lululxvi@gmail.com
License: GPL-3.0
Keywords: Command-line utility,Multiple servers,GPU,Job submission
Classifier: Development Status :: 3 - Alpha
Classifier: Intended Audience :: End Users/Desktop
Classifier: License :: OSI Approved :: GNU General Public License v3 (GPLv3)
Classifier: Programming Language :: Python :: 3 :: Only
Classifier: Topic :: Utilities
License-File: LICENSE
